midjargon/__init__.py
midjargon/__main__.py
midjargon/__version__.py
midjargon/cli/__init__.py
midjargon/cli/main.py
midjargon/core/__init__.py
midjargon/core/converter.py
midjargon/core/input.py
midjargon/core/parameters.py
midjargon/core/parser.py
midjargon/core/permutations.py
midjargon/core/type_defs.py
midjargon/engines/__init__.py
midjargon/engines/base.py
midjargon/engines/fal/__init__.py
midjargon/engines/fal/_fal.py
midjargon/engines/fal/converter.py
midjargon/engines/midjourney/__init__.py
midjargon/engines/midjourney/constants.py
midjargon/engines/midjourney/models.py
midjargon/engines/midjourney/parser/__init__.py
midjargon/engines/midjourney/parser/core.py
midjargon/engines/midjourney/parser/exceptions.py
midjargon/engines/midjourney/parser/parameters.py
midjargon/engines/midjourney/parser/validation.py
midjargon-2.2.0.dist-info/METADATA
midjargon-2.2.0.dist-info/WHEEL
midjargon-2.2.0.dist-info/entry_points.txt
midjargon-2.2.0.dist-info/licenses/LICENSE
midjargon-2.2.0.dist-info/RECORD
